modulee/__init__.py
modulee/image_processing.py
modulee/pdf_converter.py
pdf_converter_nixx-0.1.0.dist-info/METADATA
pdf_converter_nixx-0.1.0.dist-info/WHEEL
pdf_converter_nixx-0.1.0.dist-info/top_level.txt
pdf_converter_nixx-0.1.0.dist-info/RECORD
